{
  "runUrl": "https://github.com/Jordanm37/port_website/actions/runs/17433973734",
  "failedJobs": [
    "build"
  ],
  "errorLogs": [
    {
      "jobName": "build",
      "logs": "2025-09-03T12:49:38.3020780Z Current runner version: '2.328.0'\n2025-09-03T12:49:38.3045712Z ##[group]Runner Image Provisioner\n2025-09-03T12:49:38.3046905Z Hosted Compute Agent\n2025-09-03T12:49:38.3047823Z Version: 20250829.383\n2025-09-03T12:49:38.3048720Z Commit: 27cb235aab5b0e52e153a26cd86b4742e89dac5d\n2025-09-03T12:49:38.3049787Z Build Date: 2025-08-29T13:48:48Z\n2025-09-03T12:49:38.3050383Z ##[endgroup]\n2025-09-03T12:49:38.3051052Z ##[group]Operating System\n2025-09-03T12:49:38.3051639Z Ubuntu\n2025-09-03T12:49:38.3052092Z 24.04.3\n2025-09-03T12:49:38.3052647Z LTS\n2025-09-03T12:49:38.3053125Z ##[endgroup]\n2025-09-03T12:49:38.3053626Z ##[group]Runner Image\n2025-09-03T12:49:38.3054265Z Image: ubuntu-24.04\n2025-09-03T12:49:38.3054802Z Version: 20250831.1.0\n2025-09-03T12:49:38.3055804Z Included Software: https://github.com/actions/runner-images/blob/ubuntu24/20250831.1/images/ubuntu/Ubuntu2404-Readme.md\n2025-09-03T12:49:38.3057435Z Image Release: https://github.com/actions/runner-images/releases/tag/ubuntu24%2F20250831.1\n2025-09-03T12:49:38.3058528Z ##[endgroup]\n2025-09-03T12:49:38.3059842Z ##[group]GITHUB_TOKEN Permissions\n2025-09-03T12:49:38.3061700Z Contents: read\n2025-09-03T12:49:38.3062308Z Metadata: read\n2025-09-03T12:49:38.3062892Z Packages: read\n2025-09-03T12:49:38.3063405Z ##[endgroup]\n2025-09-03T12:49:38.3065611Z Secret source: Actions\n2025-09-03T12:49:38.3066434Z Prepare workflow directory\n2025-09-03T12:49:38.3404066Z Prepare all required actions\n2025-09-03T12:49:38.3443308Z Getting action download info\n2025-09-03T12:49:38.6784386Z Download action repository 'actions/checkout@v4' (SHA:08eba0b27e820071cde6df949e0beb9ba4906955)\n2025-09-03T12:49:38.7753608Z Download action repository 'actions/setup-node@v4' (SHA:49933ea5288caeca8642d1e84afbd3f7d6820020)\n2025-09-03T12:49:38.9480362Z Complete job name: build\n2025-09-03T12:49:39.0144411Z ##[group]Run actions/checkout@v4\n2025-09-03T12:49:39.0145236Z with:\n2025-09-03T12:49:39.0145646Z   repository: Jordanm37/port_website\n2025-09-03T12:49:39.0146310Z   token: ***\n2025-09-03T12:49:39.0146706Z   ssh-strict: true\n2025-09-03T12:49:39.0147126Z   ssh-user: git\n2025-09-03T12:49:39.0147544Z   persist-credentials: true\n2025-09-03T12:49:39.0147990Z   clean: true\n2025-09-03T12:49:39.0148404Z   sparse-checkout-cone-mode: true\n2025-09-03T12:49:39.0148900Z   fetch-depth: 1\n2025-09-03T12:49:39.0149474Z   fetch-tags: false\n2025-09-03T12:49:39.0149884Z   show-progress: true\n2025-09-03T12:49:39.0150312Z   lfs: false\n2025-09-03T12:49:39.0150719Z   submodules: false\n2025-09-03T12:49:39.0151153Z   set-safe-directory: true\n2025-09-03T12:49:39.0151841Z ##[endgroup]\n2025-09-03T12:49:39.1216178Z Syncing repository: Jordanm37/port_website\n2025-09-03T12:49:39.1217953Z ##[group]Getting Git version info\n2025-09-03T12:49:39.1218761Z Working directory is '/home/runner/work/port_website/port_website'\n2025-09-03T12:49:39.1220230Z [command]/usr/bin/git version\n2025-09-03T12:49:39.1327955Z git version 2.51.0\n2025-09-03T12:49:39.1353763Z ##[endgroup]\n2025-09-03T12:49:39.1367597Z Temporarily overriding HOME='/home/runner/work/_temp/9cd074fe-b00a-4442-a699-b66ff1891dda' before making global git config changes\n2025-09-03T12:49:39.1372797Z Adding repository directory to the temporary git global config as a safe directory\n2025-09-03T12:49:39.1374164Z [command]/usr/bin/git config --global --add safe.directory /home/runner/work/port_website/port_website\n2025-09-03T12:49:39.1408999Z Deleting the contents of '/home/runner/work/port_website/port_website'\n2025-09-03T12:49:39.1412809Z ##[group]Initializing the repository\n2025-09-03T12:49:39.1416566Z [command]/usr/bin/git init /home/runner/work/port_website/port_website\n2025-09-03T12:49:39.1521407Z hint: Using 'master' as the name for the initial branch. This default branch name\n2025-09-03T12:49:39.1522691Z hint: is subject to change. To configure the initial branch name to use in all\n2025-09-03T12:49:39.1523791Z hint: of your new repositories, which will suppress this warning, call:\n2025-09-03T12:49:39.1524622Z hint:\n2025-09-03T12:49:39.1525155Z hint: \tgit config --global init.defaultBranch <name>\n2025-09-03T12:49:39.1526571Z hint:\n2025-09-03T12:49:39.1527311Z hint: Names commonly chosen instead of 'master' are 'main', 'trunk' and\n2025-09-03T12:49:39.1528370Z hint: 'development'. The just-created branch can be renamed via this command:\n2025-09-03T12:49:39.1529355Z hint:\n2025-09-03T12:49:39.1529827Z hint: \tgit branch -m <name>\n2025-09-03T12:49:39.1530351Z hint:\n2025-09-03T12:49:39.1531036Z hint: Disable this message with \"git config set advice.defaultBranchName false\"\n2025-09-03T12:49:39.1532472Z Initialized empty Git repository in /home/runner/work/port_website/port_website/.git/\n2025-09-03T12:49:39.1537508Z [command]/usr/bin/git remote add origin https://github.com/Jordanm37/port_website\n2025-09-03T12:49:39.1574862Z ##[endgroup]\n2025-09-03T12:49:39.1575659Z ##[group]Disabling automatic garbage collection\n2025-09-03T12:49:39.1578619Z [command]/usr/bin/git config --local gc.auto 0\n2025-09-03T12:49:39.1606008Z ##[endgroup]\n2025-09-03T12:49:39.1606701Z ##[group]Setting up auth\n2025-09-03T12:49:39.1612784Z [command]/usr/bin/git config --local --name-only --get-regexp core\\.sshCommand\n2025-09-03T12:49:39.1641748Z [command]/usr/bin/git submodule foreach --recursive sh -c \"git config --local --name-only --get-regexp 'core\\.sshCommand' && git config --local --unset-all 'core.sshCommand' || :\"\n2025-09-03T12:49:39.2003745Z [command]/usr/bin/git config --local --name-only --get-regexp http\\.https\\:\\/\\/github\\.com\\/\\.extraheader\n2025-09-03T12:49:39.2033119Z [command]/usr/bin/git submodule foreach --recursive sh -c \"git config --local --name-only --get-regexp 'http\\.https\\:\\/\\/github\\.com\\/\\.extraheader' && git config --local --unset-all 'http.https://github.com/.extraheader' || :\"\n2025-09-03T12:49:39.2251241Z [command]/usr/bin/git config --local http.https://github.com/.extraheader AUTHORIZATION: basic ***\n2025-09-03T12:49:39.2286223Z ##[endgroup]\n2025-09-03T12:49:39.2287476Z ##[group]Fetching the repository\n2025-09-03T12:49:39.2296417Z [command]/usr/bin/git -c protocol.version=2 fetch --no-tags --prune --no-recurse-submodules --depth=1 origin +0913202606349f4e238cde5b549fdfd854bb4514:refs/remotes/pull/6/merge\n2025-09-03T12:49:39.4626423Z From https://github.com/Jordanm37/port_website\n2025-09-03T12:49:39.4627478Z  * [new ref]         0913202606349f4e238cde5b549fdfd854bb4514 -> pull/6/merge\n2025-09-03T12:49:39.4663281Z ##[endgroup]\n2025-09-03T12:49:39.4664212Z ##[group]Determining the checkout info\n2025-09-03T12:49:39.4665717Z ##[endgroup]\n2025-09-03T12:49:39.4671121Z [command]/usr/bin/git sparse-checkout disable\n2025-09-03T12:49:39.4717857Z [command]/usr/bin/git config --local --unset-all extensions.worktreeConfig\n2025-09-03T12:49:39.4747458Z ##[group]Checking out the ref\n2025-09-03T12:49:39.4751947Z [command]/usr/bin/git checkout --progress --force refs/remotes/pull/6/merge\n2025-09-03T12:49:39.4858112Z Note: switching to 'refs/remotes/pull/6/merge'.\n2025-09-03T12:49:39.4859026Z \n2025-09-03T12:49:39.4859947Z You are in 'detached HEAD' state. You can look around, make experimental\n2025-09-03T12:49:39.4861596Z changes and commit them, and you can discard any commits you make in this\n2025-09-03T12:49:39.4863161Z state without impacting any branches by switching back to a branch.\n2025-09-03T12:49:39.4863748Z \n2025-09-03T12:49:39.4864142Z If you want to create a new branch to retain commits you create, you may\n2025-09-03T12:49:39.4865039Z do so (now or later) by using -c with the switch command. Example:\n2025-09-03T12:49:39.4865653Z \n2025-09-03T12:49:39.4866026Z   git switch -c <new-branch-name>\n2025-09-03T12:49:39.4866613Z \n2025-09-03T12:49:39.4866902Z Or undo this operation with:\n2025-09-03T12:49:39.4867255Z \n2025-09-03T12:49:39.4867446Z   git switch -\n2025-09-03T12:49:39.4867717Z \n2025-09-03T12:49:39.4868140Z Turn off this advice by setting config variable advice.detachedHead to false\n2025-09-03T12:49:39.4868870Z \n2025-09-03T12:49:39.4869970Z HEAD is now at 0913202 Merge 92bb8425efdb309a7f943ada07a117f586d1bca1 into 69705f549dcf0a9030b929b83bf5f8b2b432048a\n2025-09-03T12:49:39.4871957Z ##[endgroup]\n2025-09-03T12:49:39.4902424Z [command]/usr/bin/git log -1 --format=%H\n2025-09-03T12:49:39.4924897Z 0913202606349f4e238cde5b549fdfd854bb4514\n2025-09-03T12:49:39.5184021Z ##[group]Run actions/setup-node@v4\n2025-09-03T12:49:39.5184615Z with:\n2025-09-03T12:49:39.5185019Z   node-version: 22\n2025-09-03T12:49:39.5185439Z   cache: npm\n2025-09-03T12:49:39.5185846Z   always-auth: false\n2025-09-03T12:49:39.5186289Z   check-latest: false\n2025-09-03T12:49:39.5186879Z   token: ***\n2025-09-03T12:49:39.5187307Z ##[endgroup]\n2025-09-03T12:49:39.6982510Z Found in cache @ /opt/hostedtoolcache/node/22.19.0/x64\n2025-09-03T12:49:39.6990288Z ##[group]Environment details\n2025-09-03T12:49:41.4901498Z node: v22.19.0\n2025-09-03T12:49:41.4902010Z npm: 10.9.3\n2025-09-03T12:49:41.4902419Z yarn: 1.22.22\n2025-09-03T12:49:41.4904299Z ##[endgroup]\n2025-09-03T12:49:41.4927116Z [command]/opt/hostedtoolcache/node/22.19.0/x64/bin/npm config get cache\n2025-09-03T12:49:41.7414546Z /home/runner/.npm\n2025-09-03T12:49:41.8812074Z Cache hit for: node-cache-Linux-x64-npm-051dcf0674c6fbab59613efbce6d6256123edf73d76fcf534b55ad2c66987811\n2025-09-03T12:49:42.9224272Z Received 186884021 of 186884021 (100.0%), 180.9 MBs/sec\n2025-09-03T12:49:42.9225979Z Cache Size: ~178 MB (186884021 B)\n2025-09-03T12:49:42.9273583Z [command]/usr/bin/tar -xf /home/runner/work/_temp/07f90c0f-0fcd-40ff-9a72-dd033a28a949/cache.tzst -P -C /home/runner/work/port_website/port_website --use-compress-program unzstd\n2025-09-03T12:49:43.2934188Z Cache restored successfully\n2025-09-03T12:49:43.3294460Z Cache restored from key: node-cache-Linux-x64-npm-051dcf0674c6fbab59613efbce6d6256123edf73d76fcf534b55ad2c66987811\n2025-09-03T12:49:43.3463981Z ##[group]Run npm ci\n2025-09-03T12:49:43.3464275Z \u001b[36;1mnpm ci\u001b[0m\n2025-09-03T12:49:43.3532975Z shell: /usr/bin/bash -e {0}\n2025-09-03T12:49:43.3533268Z ##[endgroup]\n2025-09-03T12:49:52.7522360Z \n2025-09-03T12:49:52.7528646Z > nick.net.au@0.1.0 prepare\n2025-09-03T12:49:52.7529038Z > husky\n2025-09-03T12:49:52.7529454Z \n2025-09-03T12:49:52.8184997Z \n2025-09-03T12:49:52.8185782Z added 642 packages, and audited 643 packages in 9s\n2025-09-03T12:49:52.8186262Z \n2025-09-03T12:49:52.8186481Z 310 packages are looking for funding\n2025-09-03T12:49:52.8186865Z   run `npm fund` for details\n2025-09-03T12:49:52.8199061Z \n2025-09-03T12:49:52.8199725Z found 0 vulnerabilities\n2025-09-03T12:49:52.9341446Z ##[group]Run npm run typecheck\n2025-09-03T12:49:52.9341765Z \u001b[36;1mnpm run typecheck\u001b[0m\n2025-09-03T12:49:52.9373111Z shell: /usr/bin/bash -e {0}\n2025-09-03T12:49:52.9373368Z ##[endgroup]\n2025-09-03T12:49:53.0357381Z \n2025-09-03T12:49:53.0358027Z > nick.net.au@0.1.0 typecheck\n2025-09-03T12:49:53.0358442Z > tsc --noEmit\n2025-09-03T12:49:53.0358600Z \n2025-09-03T12:49:57.7101083Z ##[error]components/ui/Reveal.tsx(11,10): error TS2322: Type 'RefObject<HTMLElement>' is not assignable to type 'LegacyRef<HTMLDivElement> | undefined'.\n2025-09-03T12:49:57.7110888Z   Type 'RefObject<HTMLElement>' is not assignable to type 'RefObject<HTMLDivElement>'.\n2025-09-03T12:49:57.7111968Z     Property 'align' is missing in type 'HTMLElement' but required in type 'HTMLDivElement'.\n2025-09-03T12:49:57.7521155Z ##[error]Process completed with exit code 2.\n2025-09-03T12:49:57.7624038Z Post job cleanup.\n2025-09-03T12:49:57.8568647Z [command]/usr/bin/git version\n2025-09-03T12:49:57.8605227Z git version 2.51.0\n2025-09-03T12:49:57.8647557Z Temporarily overriding HOME='/home/runner/work/_temp/01242da1-bdb8-408c-9b1d-8247cf3c5a9d' before making global git config changes\n2025-09-03T12:49:57.8648749Z Adding repository directory to the temporary git global config as a safe directory\n2025-09-03T12:49:57.8659796Z [command]/usr/bin/git config --global --add safe.directory /home/runner/work/port_website/port_website\n2025-09-03T12:49:57.8692689Z [command]/usr/bin/git config --local --name-only --get-regexp core\\.sshCommand\n2025-09-03T12:49:57.8724476Z [command]/usr/bin/git submodule foreach --recursive sh -c \"git config --local --name-only --get-regexp 'core\\.sshCommand' && git config --local --unset-all 'core.sshCommand' || :\"\n2025-09-03T12:49:57.8950457Z [command]/usr/bin/git config --local --name-only --get-regexp http\\.https\\:\\/\\/github\\.com\\/\\.extraheader\n2025-09-03T12:49:57.8971022Z http.https://github.com/.extraheader\n2025-09-03T12:49:57.8984299Z [command]/usr/bin/git config --local --unset-all http.https://github.com/.extraheader\n2025-09-03T12:49:57.9015390Z [command]/usr/bin/git submodule foreach --recursive sh -c \"git config --local --name-only --get-regexp 'http\\.https\\:\\/\\/github\\.com\\/\\.extraheader' && git config --local --unset-all 'http.https://github.com/.extraheader' || :\"\n2025-09-03T12:49:57.9372491Z Cleaning up orphan processes\n"
    }
  ]
}